ideograph/__init__.py
ideograph/ids-data.db
ideograph-1.1.0.data/scripts/ideograph
ideograph-1.1.0.dist-info/METADATA
ideograph-1.1.0.dist-info/RECORD
ideograph-1.1.0.dist-info/WHEEL
ideograph-1.1.0.dist-info/top_level.txt
