Metadata-Version: 2.1
Name: ideograph
Version: 1.1.0
Summary: Tool for finding ideographic (e.g. Han) characters from their components
Home-page: https://github.com/iwsfutcmd/ideograph
Author: Ben Yang
Author-email: benayang@gmail.com
License: UNKNOWN
Platform: UNKNOWN
Classifier: Programming Language :: Python :: 3
Classifier: License :: OSI Approved :: MIT License
Classifier: Operating System :: OS Independent
Classifier: Topic :: Text Processing :: Linguistic
Classifier: Natural Language :: Chinese (Simplified)
Classifier: Natural Language :: Chinese (Traditional)
Classifier: Natural Language :: Japanese
Classifier: Natural Language :: Korean
Classifier: Natural Language :: Vietnamese
